sucp552.py
sucp552-999.9.9.dist-info/METADATA
sucp552-999.9.9.dist-info/WHEEL
sucp552-999.9.9.dist-info/top_level.txt
sucp552-999.9.9.dist-info/RECORD
