Metadata-Version: 2.1
Name: sucp552
Version: 999.9.9
Summary: This is a demonstration of the dependency confusion vulnerability. The package does not contain anything malicoius.
Home-page: UNKNOWN
Author: UNKNOWN
Author-email: UNKNOWN
License: UNKNOWN
Platform: UNKNOWN
